{
  "version": "2.0.0",
  "tasks": [
    {
      "label": "ðŸš€ Start MCP Multi-Core Server",
      "type": "shell",
      "command": "npm",
      "args": ["run", "mcp:multicore"],
      "group": "build",
      "isBackground": true,
      "presentation": {
        "echo": true,
        "reveal": "always",
        "focus": false,
        "panel": "dedicated",
        "showReuseMessage": false,
        "clear": true
      },
      "options": {
        "cwd": "${workspaceFolder}/sveltekit-frontend"
      },
      "detail": "Start enhanced MCP multi-core server with GPU acceleration"
    },
    {
      "label": "ðŸ“Š MCP Health Check",
      "type": "shell",
      "command": "curl",
      "args": [
        "-s",
        "http://localhost:3000/mcp/health"
      ],
      "group": "test",
      "presentation": {
        "echo": true,
        "reveal": "always",
        "focus": false,
        "panel": "shared"
      },
      "detail": "Check MCP server health status"
    },
    {
      "label": "âš¡ MCP Metrics Dashboard",
      "type": "shell",
      "command": "powershell",
      "args": [
        "-NoProfile",
        "-Command",
        "Write-Host 'ðŸ“Š MCP Server Metrics Dashboard' -ForegroundColor Cyan; $health = Invoke-RestMethod -Uri 'http://localhost:3000/mcp/health'; $metrics = Invoke-RestMethod -Uri 'http://localhost:3000/mcp/metrics'; $workers = Invoke-RestMethod -Uri 'http://localhost:3000/mcp/workers'; Write-Host \"âœ… Status: $($health.status)\" -ForegroundColor Green; Write-Host \"ðŸ‘¥ Workers: $($workers.active)/$($workers.total)\" -ForegroundColor Yellow; Write-Host \"ðŸ–¥ï¸ Memory: $([math]::Round($metrics.memory.heapUsed / 1MB, 2)) MB\" -ForegroundColor Magenta; Write-Host \"â±ï¸ Uptime: $([math]::Round($health.uptime, 2))s\" -ForegroundColor Cyan"
      ],
      "group": "test",
      "presentation": {
        "echo": true,
        "reveal": "always",
        "focus": false,
        "panel": "shared"
      },
      "detail": "Display detailed MCP server metrics"
    },
    {
      "label": "ðŸ”„ Restart MCP Server",
      "type": "shell",
      "command": "powershell",
      "args": [
        "-NoProfile",
        "-Command",
        "Write-Host 'ðŸ”„ Restarting MCP Server...' -ForegroundColor Yellow; taskkill /F /IM node.exe /FI \"WINDOWTITLE eq *mcp-multicore*\" 2>$null; Start-Sleep 2; Write-Host 'âœ… Starting fresh MCP instance...' -ForegroundColor Green"
      ],
      "group": "build",
      "presentation": {
        "echo": true,
        "reveal": "always",
        "focus": false,
        "panel": "shared"
      },
      "detail": "Restart MCP multi-core server"
    }
  ]
}
